ghost/__init__.py
ghost/api/__init__.py
ghost/benchmarks/__init__.py
ghost/benchmarks/competitors.py
ghost/benchmarks/pricing_data.py
ghost/benchmarks/runner.py
ghost/benchmarks/simulator.py
ghost/cli/__init__.py
ghost/cli/main.py
ghost/core/__init__.py
ghost/core/client.py
ghost/core/config.py
ghost/core/exceptions.py
ghost/core/models.py
ghost/integrations/__init__.py
ghost/integrations/databricks.py
ghost/integrations/dataproc.py
ghost/integrations/emr.py
ghost/integrations/synapse.py
ghost/utils/__init__.py
ghost/utils/logging.py
ghost/utils/retry.py
ghost_compute-0.1.0.dist-info/licenses/LICENSE
ghost_compute-0.1.0.dist-info/METADATA
ghost_compute-0.1.0.dist-info/WHEEL
ghost_compute-0.1.0.dist-info/entry_points.txt
ghost_compute-0.1.0.dist-info/top_level.txt
ghost_compute-0.1.0.dist-info/RECORD
