Metadata-Version: 2.4
Name: ghost-compute
Version: 0.1.0
Summary: Intelligent serverless orchestration for data platforms - eliminate idle cluster waste and cold start latency
Author-email: Ghost AI <engineering@ghost-ai.io>
Maintainer-email: Ghost AI Team <team@ghost-ai.io>
License-Expression: Apache-2.0
Project-URL: Homepage, https://ghost-compute.io
Project-URL: Documentation, https://docs.ghost-compute.io
Project-URL: Repository, https://github.com/ghost-ai-dev/ghost-compute
Project-URL: Issues, https://github.com/ghost-ai-dev/ghost-compute/issues
Project-URL: Changelog, https://github.com/ghost-ai-dev/ghost-compute/blob/main/CHANGELOG.md
Keywords: databricks,spark,serverless,cloud,optimization,finops,emr,synapse,dataproc,data-engineering,cost-optimization
Classifier: Development Status :: 4 - Beta
Classifier: Intended Audience :: Developers
Classifier: Intended Audience :: System Administrators
Classifier: Operating System :: OS Independent
Classifier: Programming Language :: Python :: 3
Classifier: Programming Language :: Python :: 3.9
Classifier: Programming Language :: Python :: 3.10
Classifier: Programming Language :: Python :: 3.11
Classifier: Programming Language :: Python :: 3.12
Classifier: Topic :: System :: Distributed Computing
Classifier: Topic :: System :: Systems Administration
Classifier: Topic :: Office/Business :: Financial
Requires-Python: >=3.9
License-File: LICENSE
Requires-Dist: pydantic>=2.0.0
Requires-Dist: pydantic-settings>=2.0.0
Requires-Dist: httpx>=0.24.0
Requires-Dist: rich>=13.0.0
Requires-Dist: typer>=0.9.0
Requires-Dist: pyyaml>=6.0
Requires-Dist: structlog>=23.1.0
Requires-Dist: tenacity>=8.2.0
Requires-Dist: cachetools>=5.3.0
Requires-Dist: databricks-sdk>=0.12.0
Requires-Dist: boto3>=1.28.0
Requires-Dist: azure-identity>=1.14.0
Requires-Dist: azure-mgmt-synapse>=2.0.0
Requires-Dist: azure-mgmt-monitor>=6.0.0
Requires-Dist: google-cloud-dataproc>=5.4.0
Requires-Dist: google-auth>=2.0.0
Requires-Dist: scikit-learn>=1.3.0
Requires-Dist: pandas>=2.0.0
Requires-Dist: numpy>=1.24.0
Requires-Dist: croniter>=1.3.0
Requires-Dist: prometheus-client>=0.17.0
Provides-Extra: dev
Requires-Dist: pytest>=7.4.0; extra == "dev"
Requires-Dist: pytest-cov>=4.1.0; extra == "dev"
Requires-Dist: pytest-asyncio>=0.21.0; extra == "dev"
Requires-Dist: pytest-mock>=3.11.0; extra == "dev"
Requires-Dist: mypy>=1.5.0; extra == "dev"
Requires-Dist: black>=23.7.0; extra == "dev"
Requires-Dist: ruff>=0.0.285; extra == "dev"
Requires-Dist: pre-commit>=3.3.0; extra == "dev"
Requires-Dist: types-pyyaml>=6.0.0; extra == "dev"
Requires-Dist: types-cachetools>=5.3.0; extra == "dev"
Requires-Dist: build>=1.0.0; extra == "dev"
Requires-Dist: twine>=4.0.0; extra == "dev"
Provides-Extra: docs
Requires-Dist: mkdocs>=1.5.0; extra == "docs"
Requires-Dist: mkdocs-material>=9.2.0; extra == "docs"
Requires-Dist: mkdocstrings[python]>=0.22.0; extra == "docs"
Provides-Extra: all
Requires-Dist: ghost-compute[dev,docs]; extra == "all"
Dynamic: license-file
